<?xml version="1.0" encoding="UTF-8"?>
<algorithms version="110505">
<algorithm name="SectLabel" version="110505">
<variant no="0" confidence="0.000000">
<sectionHeader confidence="0.522308" genericHeader="method">
TITLE INDEX
</sectionHeader>
<note confidence="0.567456">
VOLUMES 6- 13
</note>
<title confidence="0.411936666666667">
Algorithm for Generating Quantifier Scopings
Hobbs, Jerry R. and Shieber, Stuart M.
Analyzing the Structure of Argumentative Discourse
</title>
<author confidence="0.344704">
Cohen, Robin
</author>
<title confidence="0.409805">
Applied Computational Linguistics in Perspective: Proceedings of the Workshop
</title>
<author confidence="0.375486">
Johnson, Carroll and Bachenko, Joan
</author>
<title confidence="0.663349">
Associative Model of Morphological Analysis: An Empirical Inquiry
</title>
<author confidence="0.577497">
Jappinen, Harri and Ylilammi, Matti
</author>
<affiliation confidence="0.173783">
Attention, Intentions, and the Structure of Discourse
</affiliation>
<note confidence="0.641009">
Grosz, Barbara J. and Sidner, Candace I.
</note>
<title confidence="0.317969285714286">
Automated Translation at Grenoble University
Vauquois, Bernard and Boitet, Christian
Cascaded ATN Grammars
Woods, William A.
Chacterizing Indirect Speech Acts
Brown, Gretchen P.
Comments on Pullum&apos;s Criticisms
</title>
<note confidence="0.555285">
Langendoen, D. Terence and Postal, Paul M.
</note>
<title confidence="0.529591">
Commonsense Metaphysics and Lexical Semantics
</title>
<author confidence="0.501838">
Hobbs, Jerry R.; Croft, William; Davies, Todd; Edwards, Douglas; and Laws, Kenneth
</author>
<subsectionHeader confidence="0.293208">
Computational Complexity and Lexical-Functional Grammar
</subsectionHeader>
<bodyText confidence="0.408639">
Berwick, Robert C.
</bodyText>
<subsectionHeader confidence="0.867175">
Computer Generation of Multiparagraph English Text
</subsectionHeader>
<bodyText confidence="0.846095">
Mann, William C. and Moore, James A.
</bodyText>
<subsectionHeader confidence="0.638157">
Computing Story Trees
</subsectionHeader>
<bodyText confidence="0.39686">
Correira, Alfred
</bodyText>
<subsectionHeader confidence="0.595011">
Concept Extraction, from Proceedings of the Workshop on Applied Computational Linguistics
</subsectionHeader>
<bodyText confidence="0.629937">
in Perspective
</bodyText>
<sectionHeader confidence="0.78876" genericHeader="method">
Montgomery, Christine (Chair)
</sectionHeader>
<subsectionHeader confidence="0.971827">
Coping with Syntactic Ambiguity or How to Put the Block in the Box on the Table
</subsectionHeader>
<bodyText confidence="0.901349">
Church, Kenneth and Patil, Ramesh
</bodyText>
<subsectionHeader confidence="0.9496045">
Correction of Ill-Formed Input Using History-Basec Expectation with Applications to Speech
Understanding, The
</subsectionHeader>
<bodyText confidence="0.534246">
Fink, Pamela E. and Biermann, Alan W.
</bodyText>
<sectionHeader confidence="0.273393" genericHeader="method">
Denotational Semantics for &amp;quot;Natural&amp;quot; Language Question-Answering Programs
</sectionHeader>
<subsectionHeader confidence="0.7223905">
Main, Michael G. and Benson, David B.
Determining Verb Phrase Referents in Dialogs
Robinson, Ann E.
Disambiguating Prepositional Phrase by Using On-Line Dictionary Definitions
</subsectionHeader>
<bodyText confidence="0.635014">
Jensen, Karen and Binot, Jean-Louis
</bodyText>
<subsectionHeader confidence="0.625741">
Discourse-Oriented Anaphora Resolution: A Review
</subsectionHeader>
<bodyText confidence="0.510231">
Hirst, Graeme
</bodyText>
<sectionHeader confidence="0.65603" genericHeader="method">
Discourse Procedures for Sublanguage Selectional Patterns: Initial Experiments
</sectionHeader>
<keyword confidence="0.357399">
Grishman, Ralph; Hirschman, Lynette; and Nhan, Ngo Thanh
</keyword>
<subsectionHeader confidence="0.945009">
Efficient Augmented-Context-Free Parsing Algorithm
</subsectionHeader>
<bodyText confidence="0.520891">
Tomita, Masaru
</bodyText>
<subsectionHeader confidence="0.986235">
Efficient Easily Adaptable System for Interpreting Natural Language Queries, An
</subsectionHeader>
<bodyText confidence="0.756912">
Warren, David H.D. and Pereira, Fernando C.N.
English and the Class of Context-Free Languages
Postal, Paul M. and Langendoen, D. Terence
</bodyText>
<subsectionHeader confidence="0.591903">
Extraposition Grammars
</subsectionHeader>
<bodyText confidence="0.424068">
Pereira, Fernando
</bodyText>
<figure confidence="0.860896941176471">
13(1-2): 47-63
13(1-2): 11-24
8(2): 55-84
12(4): 257-272
12(3): 175-204
11(1): 28-36
6(1): 1-12
6(3-4): 150-166
10(3-4): 187-188
13(3-4): 241-250
8(3-4): 97-109
7(1): 17-29
6(3-4): 135-149
8(2): 70-73
8(3-4): 139-149
12(1): 13-36
9(1): 11-21
</figure>
<footnote confidence="0.9437065">
7(1): 1-16
13(3-4): 251-260
7(2): 85-98
12(3): 205-215
13(1-2): 31-46
8(3-4): 110-122
10(3-4): 177-181
7(4): 243-256
</footnote>
<page confidence="0.727736">
78 Computational Linguistics, Volume 14, Number 1, Winter 1988
</page>
<table confidence="0.45633">
Title Index Volumes 6 — 13
</table>
<subsectionHeader confidence="0.692871">
Flexible Parsing
</subsectionHeader>
<bodyText confidence="0.859681954545454">
Hayes, Philip J. and Mouradian, George V. 7(4): 232-242
Focusing for Interpretation of Pronouns
Sidner, Candace I. 7(4): 217-231
Formal Basis for Performance Evaluation of Natural Language Understanding Systems, A
Guida, Giovanni and Mauri, Giancarlo 10(1): 15-30
Formal Lexicon in the Meaning-Text Theory (or How to Do Lexica with Words), A
MeMilk, Igor A. and Polguere, Alain 13(3-4): 261-275
From English to Logic: Context-Free Computation of &apos;Conventional&apos; Logical Translation
Schubert, Lenhart and Pelletier, Francis J. 8(1): 27-44
Generalized Augmented Transition Network Grammars for Generation from Semantic Net-
works
Shapiro, Stuart C. 8(1): 12-26
Integrated Processing Produces Robust Understanding
Selfridge, Mallory 12(2): 89-106
Integrated Understander, An
Schank, Roger C.; Lebowitz, Michael; and Birnbaum, Lawrence 6(1): 13-30
Knowledge Representation Approach to Understanding Metaphors, A.
Weiner, E. Judith 10(1): 1-14
Large Lexicons for Natural Language Processing: Utilising the Grammar Coding System of
LDOCE
Boguraev, Bran and Briscoe, Ted 13(3-4): 203-218
Machine Translation, from Proceedings of the Workshop on Applied Computational Linguis-
tics in Perspective
Kay, Martin (Chair) 8(2): 74-78
Meaning of OF and HAVE in the USL System, The
Zoeppritz, Magdalena 7(2): 109-119
Meta-Rules as a Basis for Processing III-Formed Output
Weischedel, Ralph M. and Sondheimer, Norman K. 9(3-4): 161-177
Natural Language Access to Data Bases: Interpreting Update Requests
Davidson, James and Kaplan, S. Jerrold 9(2): 57-68
Natural Language Interface, from Proceedings of the Workshop on Applied Computational
Linguistics in Perspective
Hendrix, Gary G. (Chair) 8(2): 56-61
NOMAD System: Expectation-Based Detection and Correction of Errors during Understand-
ing of Syntactically and Semantically Ill-Formed Text, The
Granger, Richard H. 9(3-4): 188-196
On the Complexity of ID/LP Parsing
Barton, G. Edward Jr. 11(4): 205-218
On the Mathematical Properties of Linguistic Theories
Perrault, C. Raymond 10(3-4): 165-176
On Two Recent Attempts to Show that English is Not a CFL
Pullum, Geoffrey K. 10(3-4): 182-186
Operating Statistics for the Transformational Question Answering System
Damerau, Fred J. 7(1): 30-42
</bodyText>
<subsectionHeader confidence="0.922997">
Paraphrasing Questions Using Given and New Information
</subsectionHeader>
<bodyText confidence="0.8635055">
McKeown, Kathleen R. 9(1): 1-10
Parse Fitting and Prose Fixing: Getting a Hold on Ill-Formedness
</bodyText>
<reference confidence="0.3533428">
Jensen, Karen; Heidorn, George E.; Miller, Lance A.; and Ravin, Yael 9(3-4): 147-160
Parsing Algorithm that Extends Phrases, A.
Chester, Daniel 6(2): 87-96
Phrase-Structured Grammatical Framework for Transportable Natural Language
Processing, A.
Ballard, Bruce W. and Tinkham, Nancy L. 10(2): 81-96
Phrase Structure Trees Bear More Fruit than You Would Have Thought
Joshi, Aravind and Levy, Leon S. 8(1): 1-11
PHRED: A Generator for Natural Language Interfaces
Jacobs, Paul S. 11(4): 219-242
</reference>
<footnote confidence="0.24722">
Computational Linguistics, Volume 14, Number 1, Winter 1988 79
Title Index Volumes 6 — 13
</footnote>
<note confidence="0.897656">
Plan-Based Analysis of Indirect Speech Acts, A.
Perrault, C. Raymond and Allen, James F. 6(3-4): 167-182
Pragmatics of Referring and the Modality of Communication, The
Cohen, Philip R. 10(2): 97-146
Preference Semantics, Ill-Formedness, and Metaphor
Fass, Dan and Wilks, Yorick 9(3-4): 178-187
</note>
<subsectionHeader confidence="0.21436">
Processing Dictionary Definitions with Phrasal Pattern Hierarchies
</subsectionHeader>
<bodyText confidence="0.421453">
Alshawi, Hiyan 13(3-4): 195-202
</bodyText>
<subsectionHeader confidence="0.763465">
Prospects for Computer-Assisted Dialect Adaptation
</subsectionHeader>
<bodyText confidence="0.857507">
Webber, David J. and Mann, William C. 7(3): 165-177
</bodyText>
<sectionHeader confidence="0.77674" genericHeader="method">
Recovery Strategies for Parsing Extragrammatical Language
</sectionHeader>
<reference confidence="0.957560804347826">
Carbonell, Jaime G. and Hayes, Philip 9(3-4): 123-146
Reference Identification and Reference Identification Failures
Goodman, Bradley A. 12(4): 273-305
Relaxation Theories for Parsing Ill-Formed Input
Kwasny, Stan C. and Sondheimer, Norman K. 7(2): 99-108
Resolving Lexical Ambiguity in a Deterministic Parser
Milne, Robert 12(1): 1-12
Responding Intelligently to Unparsable Inputs
Weischedel, Ralph M. and Black, John E. 6(2): 87-109
Restricting Logic Grammars with Government-Binding Theory
Stabler, Edward P. 13(1-2): 1-10
Roles, Co-Descriptors, and the Formal Representation of Quantified English Expressions
Martin, William A. 7(3): 137-147
Self-Extending Phrasal Lexicon, The
Zernik, Uri and Dyer, Michael G. 13(3-4):
Simultaneous-Distributive Co-ordination and Context-Freeness
Kac, Michael B.; Manaster-Ramer, Alexis; and Rounds, William C. 13(1-2): 25-30
Slot Grammars
McCord, Michael C. 6(1): 31-43
Strong Generative Capacity, Weak Generative Capacity, and Modern Linguistic Theories
Berwick, Robert C. 10(3-4): 189-202
Sublanguages, from Proceedings of the Workshop on Applied Computational Linguistics in
Perspective
Kittredge, Richard (Chair) 8(2): 79-82
Subworld Concept Lexicon and the Lexicon Management System, The
Nirenburg, Sergei and Raskin, Victor 13(3-4): 276-289
Summarizing Natural Language Database Responses
Kalita, Jugal K.; Jones, Marlene L.; and McCalla, Gordon I. 12(2): 107-124
Survey of Machine Translation: Its History, Current Status, and Future Prospects, A.
Slocum, Jonathan 11(1): 1-17
TAUM-AVIATION: Its Technical Features and Some Experimental Results
Isabelle, Pierre and Bourbeau, Laurent 11(1): 18-27
Text Generation, from Proceedings of the Workshop on Applied Computational Linguistics in
Perspective
Mann, William (Chair) 8(2): 62-69
Tools and Methods for Computational Lexicology
Byrd, Roy J.; Calzolari, Nicoletta; Chodorow, Martin S.; Klavans, Judith L.; Neff,
Mary S.; and Rizk, Omneya 13(3-4): 203-218
Toward Natural Language Computation
Biermann, Alan W. and Ballard, Bruce W. 6(2): 71-86
Translating Spanish into Logic through Logic
Dahl, Veronica 7(3): 149-164
Treating Coordination in Logic Grammars
Dahl, Veronica and McCord, Michael C. 9(2): 69-91
Using Semantics in Non-Context-Free Parsing of Montague Grammar
Warren, David Scott and Friedman, Joyce 8(3-4): 123-138
</reference>
<page confidence="0.959211">
80 Computational Linguistics, Volume 14, Number 1, Winter 1988
</page>
</variant>
</algorithm>
<algorithm name="ParsHed" version="110505">
<variant no="0" confidence="0.000000">
<title confidence="0.782278">INDEX</title>
<note confidence="0.562631">VOLUMES 6- 13</note>
<title confidence="0.590811">Algorithm for Generating Quantifier Scopings</title>
<degree confidence="0.5832535">Hobbs, Jerry R. and Shieber, Stuart M. Analyzing the Structure of Argumentative Discourse Cohen, Robin Applied Computational Linguistics in Perspective: Proceedings of the Workshop Johnson, Carroll and Bachenko, Joan of Morphological Analysis: An Empirical Inquiry Jappinen, Harri and Ylilammi, Matti Attention, Intentions, and the Structure of Discourse</degree>
<affiliation confidence="0.81542">Grosz, Barbara J. and Sidner, Candace I. Automated Translation at Grenoble University</affiliation>
<address confidence="0.77813">Vauquois, Bernard and Boitet, Christian</address>
<note confidence="0.574315">Grammars Woods, William A. Chacterizing Indirect Speech Acts Gretchen Comments on Pullum&apos;s Criticisms Langendoen, D. Terence and Postal, Paul M.</note>
<title confidence="0.837711">Commonsense Metaphysics and Lexical Semantics</title>
<author confidence="0.982736">R Jerry</author>
<author confidence="0.982736">William Croft</author>
<author confidence="0.982736">Todd Davies</author>
<author confidence="0.982736">Douglas Edwards</author>
<author confidence="0.982736">Laws</author>
<affiliation confidence="0.976557">Computational Complexity and Lexical-Functional Grammar</affiliation>
<address confidence="0.621317">Berwick, Robert C.</address>
<affiliation confidence="0.88655">Computer Generation of Multiparagraph English Text</affiliation>
<address confidence="0.549351">Mann, William C. and Moore, James A.</address>
<affiliation confidence="0.735285">Computing Story Trees</affiliation>
<address confidence="0.891641">Correira, Alfred</address>
<title confidence="0.75315425">Concept Extraction, from Proceedings of the Workshop on Applied Computational Linguistics in Perspective Montgomery, Christine (Chair) Coping with Syntactic Ambiguity or How to Put the Block in the Box on the Table</title>
<author confidence="0.977108">Kenneth Church</author>
<author confidence="0.977108">Ramesh Patil</author>
<affiliation confidence="0.873847333333333">Correction of Ill-Formed Input Using History-Basec Expectation with Applications to Speech Understanding, The Fink, Pamela E. and Biermann, Alan W.</affiliation>
<title confidence="0.95758">Denotational Semantics for &amp;quot;Natural&amp;quot; Language Question-Answering Programs</title>
<author confidence="0.987564">G Michael</author>
<author confidence="0.987564">David Benson</author>
<affiliation confidence="0.4453535">Determining Verb Phrase Referents in Dialogs Robinson, Ann E.</affiliation>
<title confidence="0.409989">Disambiguating Prepositional Phrase by Using On-Line Dictionary Definitions Jensen, Karen and Binot, Jean-Louis Discourse-Oriented Anaphora Resolution: A Review Hirst, Graeme Discourse Procedures for Sublanguage Selectional Patterns: Initial Experiments Grishman, Ralph; Hirschman, Lynette; and Nhan, Ngo Thanh Efficient Augmented-Context-Free Parsing Algorithm</title>
<author confidence="0.531076">Masaru Tomita</author>
<affiliation confidence="0.437768">Easily Adaptable Interpreting Natural Language Queries, An</affiliation>
<address confidence="0.431253">Warren, David H.D. and Pereira, Fernando C.N.</address>
<title confidence="0.828595">and the Context-Free Languages</title>
<author confidence="0.877553">Paul M Postal</author>
<author confidence="0.877553">D Terence Langendoen</author>
<affiliation confidence="0.795652">Extraposition Grammars</affiliation>
<address confidence="0.810702">Pereira, Fernando</address>
<phone confidence="0.98373084">13(1-2): 47-63 13(1-2): 11-24 8(2): 55-84 12(4): 257-272 12(3): 175-204 11(1): 28-36 6(1): 1-12 6(3-4): 150-166 10(3-4): 187-188 13(3-4): 241-250 8(3-4): 97-109 7(1): 17-29 6(3-4): 135-149 8(2): 70-73 8(3-4): 139-149 12(1): 13-36 9(1): 11-21 7(1): 1-16 13(3-4): 251-260 7(2): 85-98 12(3): 205-215 13(1-2): 31-46 8(3-4): 110-122 10(3-4): 177-181 7(4): 243-256</phone>
<date confidence="0.651481">78 Computational Linguistics, Volume 14, Number 1, Winter 1988</date>
<title confidence="0.8007905">Index Volumes 6 — 13 Flexible Parsing</title>
<author confidence="0.980976">J Philip</author>
<author confidence="0.980976">George V Mouradian</author>
<note confidence="0.584112647058823">Focusing for Interpretation of Pronouns Candace I. 7(4): Formal Basis for Performance Evaluation of Natural Language Understanding Systems, A Giovanni and Mauri, Giancarlo 10(1): Lexicon in the Theory (or How to Do Lexica with Words), A Igor A. and Polguere, Alain English to Logic: Computation of &apos;Conventional&apos; Logical Translation Lenhart and Pelletier, Francis J. 8(1): Generalized Augmented Transition Network Grammars for Generation from Semantic Networks Stuart C. 8(1): Integrated Processing Produces Robust Understanding Mallory 12(2): Integrated Understander, An Roger C.; Lebowitz, Michael; and Birnbaum, Lawrence 6(1): Knowledge Representation Approach to Understanding Metaphors, A. E. Judith 10(1):</note>
<title confidence="0.8596065">Large Lexicons for Natural Language Processing: Utilising the Grammar Coding System of LDOCE</title>
<author confidence="0.443846">Bran</author>
<author confidence="0.443846">Ted Briscoe</author>
<note confidence="0.4206164">Machine Translation, from Proceedings of the Workshop on Applied Computational Linguistics in Perspective Martin (Chair) 8(2): Meaning of OF and HAVE in the USL System, The Magdalena 7(2):</note>
<title confidence="0.939169">as a Basis for Processing Output</title>
<author confidence="0.979627">M Ralph</author>
<author confidence="0.979627">Norman K Sondheimer</author>
<title confidence="0.932925">Natural Language Access to Data Bases: Interpreting Update Requests</title>
<author confidence="0.554837">James</author>
<author confidence="0.554837">S Jerrold Kaplan</author>
<title confidence="0.919359">Natural Language Interface, from Proceedings of the Workshop on Applied Computational Linguistics in Perspective</title>
<author confidence="0.861518">G Gary</author>
<title confidence="0.5334075">NOMAD System: Expectation-Based Detection and Correction of Errors during Understanding of Syntactically and Semantically Ill-Formed Text, The</title>
<author confidence="0.982707">H Richard</author>
<title confidence="0.984968">On the Complexity of ID/LP Parsing</title>
<title confidence="0.999836">On the Mathematical Properties of Linguistic Theories</title>
<author confidence="0.984868">C Raymond</author>
<title confidence="0.78647">On Two Recent Attempts to Show that English is Not a CFL</title>
<author confidence="0.94449">K Geoffrey</author>
<title confidence="0.994918">Operating Statistics for the Transformational Question Answering System</title>
<author confidence="0.995036">J Fred</author>
<title confidence="0.996948">Paraphrasing Questions Using Given and New Information</title>
<author confidence="0.984036">R Kathleen</author>
<note confidence="0.797534714285714">Fitting and Prose Fixing: Getting a Hold on Karen; Heidorn, George E.; Miller, Lance A.; and Ravin, Yael Parsing Algorithm that Extends Phrases, A. Daniel 6(2): Phrase-Structured Grammatical Framework for Transportable Natural Language Processing, A. Bruce W. and Tinkham, Nancy L. 10(2):</note>
<title confidence="0.513455666666667">Phrase Structure Trees Bear More Fruit than You Would Have Thought Aravind and Levy, Leon S. 8(1): PHRED: A Generator for Natural Language Interfaces</title>
<note confidence="0.885049">Jacobs, Paul S. 11(4): 219-242 Computational Linguistics, Volume 14, Number 1, Winter 1988 79 Title Index Volumes 6 — 13 Analysis of Indirect Speech Acts, C. Raymond and Allen, James F.</note>
<title confidence="0.772083">Pragmatics of Referring and the Modality of Communication, The</title>
<author confidence="0.899619">R Philip</author>
<title confidence="0.9694618">Preference Semantics, Ill-Formedness, and Metaphor Dan and Wilks, Yorick Processing Dictionary Definitions with Phrasal Pattern Hierarchies Hiyan for Dialect Adaptation</title>
<author confidence="0.997564">J David</author>
<author confidence="0.997564">William C Mann</author>
<title confidence="0.943686">Recovery Strategies for Parsing Extragrammatical Language</title>
<author confidence="0.993123">G Jaime</author>
<author confidence="0.993123">Philip Hayes</author>
<title confidence="0.901053">Reference Identification and Reference Identification Failures</title>
<author confidence="0.950255">A Bradley</author>
<title confidence="0.967299">Theories for Parsing Input</title>
<author confidence="0.950156">C Stan</author>
<author confidence="0.950156">Norman K Sondheimer</author>
<title confidence="0.918363">Resolving Lexical Ambiguity in a Deterministic Parser</title>
<author confidence="0.694499">Robert</author>
<title confidence="0.995715">Responding Intelligently to Unparsable Inputs</title>
<author confidence="0.99852">M Ralph</author>
<author confidence="0.99852">John E Black</author>
<title confidence="0.966898">Logic Grammars with Theory</title>
<author confidence="0.992168">P Edward</author>
<title confidence="0.96003">and the Formal Representation of Quantified English Expressions</title>
<author confidence="0.674067666666667">William A Phrasal Lexicon</author>
<author confidence="0.674067666666667">The Uri</author>
<author confidence="0.674067666666667">Michael G Dyer</author>
<affiliation confidence="0.733694">and</affiliation>
<author confidence="0.607672">B Michael</author>
<author confidence="0.607672">Alexis</author>
<author confidence="0.607672">William C Rounds</author>
<title confidence="0.931146">Slot Grammars</title>
<author confidence="0.986803">C Michael</author>
<title confidence="0.98423">Strong Generative Capacity, Weak Generative Capacity, and Modern Linguistic Theories</title>
<author confidence="0.988489">C Robert</author>
<note confidence="0.315962">Sublanguages, from Proceedings of the Workshop on Applied Computational Linguistics in Perspective Richard (Chair) 8(2):</note>
<title confidence="0.696523">Concept Lexicon and the Lexicon Management The Sergei and Raskin, Victor Summarizing Natural Language Database Responses</title>
<author confidence="0.45394">K Jugal</author>
<author confidence="0.45394">Marlene L Jones</author>
<author confidence="0.45394">Gordon I McCalla</author>
<note confidence="0.9632705">Survey of Machine Translation: Its History, Current Status, and Future Prospects, A. Jonathan 11(1):</note>
<title confidence="0.579855833333333">Its Features and Some Experimental Results Pierre and Bourbeau, Laurent 11(1): Text Generation, from Proceedings of the Workshop on Applied Computational Linguistics in Perspective William (Chair) 8(2): Tools and Methods for Computational Lexicology</title>
<author confidence="0.512284">Roy J Byrd</author>
<author confidence="0.512284">Nicoletta Calzolari</author>
<author confidence="0.512284">Martin S Chodorow</author>
<author confidence="0.512284">Judith L Klavans</author>
<author confidence="0.512284">Mary S Neff</author>
<author confidence="0.512284">Omneya Rizk</author>
<title confidence="0.996815">Toward Natural Language Computation</title>
<author confidence="0.980266">W Alan</author>
<author confidence="0.980266">Bruce W Ballard</author>
<title confidence="0.810822">Translating Spanish into Logic through Logic Veronica 7(3): Treating Coordination in Logic Grammars</title>
<author confidence="0.6691855">Veronica</author>
<author confidence="0.6691855">Michael C Semantics in Parsing of Montague Grammar McCord</author>
<address confidence="0.823706">Warren, David Scott and Friedman, Joyce 8(3-4): 123-138 80 Computational Linguistics, Volume 14, Number 1, Winter 1988</address>
</variant>
</algorithm>
<algorithm name="ParsCit" version="110505">
<citationList>
<citation valid="false">
<authors>
<author>Karen Jensen</author>
<author>George E Heidorn</author>
<author>Lance A Miller</author>
<author>Ravin</author>
</authors>
<title>Yael 9(3-4): 147-160 Parsing Algorithm that Extends Phrases,</title>
<publisher>A.</publisher>
<marker>Jensen, Heidorn, Miller, Ravin, </marker>
<rawString>Jensen, Karen; Heidorn, George E.; Miller, Lance A.; and Ravin, Yael 9(3-4): 147-160 Parsing Algorithm that Extends Phrases, A.</rawString>
</citation>
<citation valid="false">
<authors>
<author>Daniel Chester</author>
</authors>
<title>6(2): 87-96 Phrase-Structured Grammatical Framework for Transportable Natural Language Processing,</title>
<publisher>A.</publisher>
<marker>Chester, </marker>
<rawString>Chester, Daniel 6(2): 87-96 Phrase-Structured Grammatical Framework for Transportable Natural Language Processing, A.</rawString>
</citation>
<citation valid="false">
<authors>
<author>Bruce W Ballard</author>
<author>Nancy L Tinkham</author>
</authors>
<journal>Phrase Structure Trees Bear More Fruit than You Would Have Thought Joshi, Aravind</journal>
<volume>10</volume>
<issue>2</issue>
<pages>81--96</pages>
<marker>Ballard, Tinkham, </marker>
<rawString>Ballard, Bruce W. and Tinkham, Nancy L. 10(2): 81-96 Phrase Structure Trees Bear More Fruit than You Would Have Thought Joshi, Aravind and Levy, Leon S. 8(1): 1-11</rawString>
</citation>
<citation valid="false">
<title>PHRED: A Generator for Natural Language Interfaces Jacobs,</title>
<journal>Paul S.</journal>
<volume>11</volume>
<issue>4</issue>
<pages>219--242</pages>
<marker></marker>
<rawString>PHRED: A Generator for Natural Language Interfaces Jacobs, Paul S. 11(4): 219-242</rawString>
</citation>
<citation valid="false">
<authors>
<author>Jaime G Carbonell</author>
<author>Philip Hayes</author>
</authors>
<title>9(3-4): 123-146 Reference Identification and Reference Identification Failures</title>
<marker>Carbonell, Hayes, </marker>
<rawString>Carbonell, Jaime G. and Hayes, Philip 9(3-4): 123-146 Reference Identification and Reference Identification Failures</rawString>
</citation>
<citation valid="false">
<authors>
<author>Bradley A Goodman</author>
</authors>
<title>Relaxation Theories for Parsing Ill-Formed Input</title>
<volume>12</volume>
<issue>4</issue>
<pages>273--305</pages>
<marker>Goodman, </marker>
<rawString>Goodman, Bradley A. 12(4): 273-305 Relaxation Theories for Parsing Ill-Formed Input</rawString>
</citation>
<citation valid="false">
<authors>
<author>Stan C Kwasny</author>
<author>Norman K Sondheimer</author>
</authors>
<title>Resolving Lexical Ambiguity in a Deterministic Parser Milne,</title>
<journal>Robert</journal>
<volume>7</volume>
<issue>2</issue>
<pages>99--108</pages>
<marker>Kwasny, Sondheimer, </marker>
<rawString>Kwasny, Stan C. and Sondheimer, Norman K. 7(2): 99-108 Resolving Lexical Ambiguity in a Deterministic Parser Milne, Robert 12(1): 1-12</rawString>
</citation>
<citation valid="false">
<title>Responding Intelligently to Unparsable Inputs</title>
<marker></marker>
<rawString>Responding Intelligently to Unparsable Inputs</rawString>
</citation>
<citation valid="false">
<authors>
<author>Ralph M Weischedel</author>
<author>John E Black</author>
</authors>
<title>Restricting Logic Grammars with Government-Binding Theory Stabler, Edward P.</title>
<volume>6</volume>
<issue>2</issue>
<pages>87--109</pages>
<marker>Weischedel, Black, </marker>
<rawString>Weischedel, Ralph M. and Black, John E. 6(2): 87-109 Restricting Logic Grammars with Government-Binding Theory Stabler, Edward P. 13(1-2): 1-10</rawString>
</citation>
<citation valid="false">
<authors>
<author>Co-Descriptors Roles</author>
</authors>
<title>and the Formal Representation of Quantified English Expressions Martin,</title>
<journal>William A.</journal>
<volume>7</volume>
<issue>3</issue>
<pages>137--147</pages>
<marker>Roles, </marker>
<rawString>Roles, Co-Descriptors, and the Formal Representation of Quantified English Expressions Martin, William A. 7(3): 137-147</rawString>
</citation>
<citation valid="false">
<authors>
<author>Self-Extending Phrasal Lexicon</author>
<author>The Zernik</author>
<author>Uri</author>
<author>Michael G Dyer</author>
</authors>
<title>13(3-4): Simultaneous-Distributive Co-ordination and Context-Freeness</title>
<pages>13--1</pages>
<marker>Lexicon, Zernik, Uri, Dyer, </marker>
<rawString>Self-Extending Phrasal Lexicon, The Zernik, Uri and Dyer, Michael G. 13(3-4): Simultaneous-Distributive Co-ordination and Context-Freeness Kac, Michael B.; Manaster-Ramer, Alexis; and Rounds, William C. 13(1-2): 25-30</rawString>
</citation>
<citation valid="false">
<authors>
<author>Slot Grammars McCord</author>
<author>C Michael</author>
</authors>
<volume>6</volume>
<issue>1</issue>
<pages>31--43</pages>
<marker>McCord, Michael, </marker>
<rawString>Slot Grammars McCord, Michael C. 6(1): 31-43</rawString>
</citation>
<citation valid="false">
<authors>
<author>Strong Generative</author>
</authors>
<title>Capacity, Weak Generative Capacity, and Modern Linguistic Theories Berwick, Robert C.</title>
<pages>10--3</pages>
<marker>Generative, </marker>
<rawString>Strong Generative Capacity, Weak Generative Capacity, and Modern Linguistic Theories Berwick, Robert C. 10(3-4): 189-202</rawString>
</citation>
<citation valid="false">
<booktitle>Sublanguages, from Proceedings of the Workshop on Applied Computational Linguistics in Perspective</booktitle>
<marker></marker>
<rawString>Sublanguages, from Proceedings of the Workshop on Applied Computational Linguistics in Perspective</rawString>
</citation>
<citation valid="false">
<authors>
<author>Richard Kittredge</author>
</authors>
<title>(Chair) 8(2): 79-82 Subworld Concept Lexicon and the Lexicon Management System, The Nirenburg, Sergei and Raskin, Victor 13(3-4):</title>
<pages>276--289</pages>
<marker>Kittredge, </marker>
<rawString>Kittredge, Richard (Chair) 8(2): 79-82 Subworld Concept Lexicon and the Lexicon Management System, The Nirenburg, Sergei and Raskin, Victor 13(3-4): 276-289</rawString>
</citation>
<citation valid="false">
<authors>
<author>K Jones</author>
<author>L Marlene</author>
<author>Gordon I McCalla</author>
</authors>
<title>Summarizing Natural Language Database Responses Kalita, Jugal</title>
<journal>Survey of Machine Translation: Its History, Current Status, and Future Prospects, A. Slocum, Jonathan</journal>
<volume>12</volume>
<issue>2</issue>
<pages>107--124</pages>
<marker>Jones, Marlene, McCalla, </marker>
<rawString>Summarizing Natural Language Database Responses Kalita, Jugal K.; Jones, Marlene L.; and McCalla, Gordon I. 12(2): 107-124 Survey of Machine Translation: Its History, Current Status, and Future Prospects, A. Slocum, Jonathan 11(1): 1-17</rawString>
</citation>
<citation valid="false">
<title>TAUM-AVIATION: Its Technical Features and Some Experimental Results Isabelle,</title>
<journal>Pierre and Bourbeau, Laurent</journal>
<volume>11</volume>
<issue>1</issue>
<pages>18--27</pages>
<marker></marker>
<rawString>TAUM-AVIATION: Its Technical Features and Some Experimental Results Isabelle, Pierre and Bourbeau, Laurent 11(1): 18-27</rawString>
</citation>
<citation valid="false">
<authors>
<author>Text Generation</author>
</authors>
<booktitle>from Proceedings of the Workshop on Applied Computational Linguistics in Perspective</booktitle>
<marker>Generation, </marker>
<rawString>Text Generation, from Proceedings of the Workshop on Applied Computational Linguistics in Perspective</rawString>
</citation>
<citation valid="false">
<authors>
<author>William Mann</author>
</authors>
<title>(Chair)</title>
<booktitle>Tools and Methods for Computational Lexicology</booktitle>
<volume>8</volume>
<issue>2</issue>
<pages>62--69</pages>
<marker>Mann, </marker>
<rawString>Mann, William (Chair) 8(2): 62-69 Tools and Methods for Computational Lexicology</rawString>
</citation>
<citation valid="false">
<authors>
<author>Roy J Byrd</author>
<author>Nicoletta Calzolari</author>
<author>Martin S Chodorow</author>
<author>Judith L Klavans</author>
<author>Neff</author>
</authors>
<marker>Byrd, Calzolari, Chodorow, Klavans, Neff, </marker>
<rawString>Byrd, Roy J.; Calzolari, Nicoletta; Chodorow, Martin S.; Klavans, Judith L.; Neff,</rawString>
</citation>
<citation valid="false">
<authors>
<author>S Mary</author>
<author>Rizk</author>
</authors>
<title>Omneya 13(3-4): 203-218 Toward Natural Language Computation</title>
<marker>Mary, Rizk, </marker>
<rawString>Mary S.; and Rizk, Omneya 13(3-4): 203-218 Toward Natural Language Computation</rawString>
</citation>
<citation valid="false">
<authors>
<author>Alan W Biermann</author>
<author>Bruce W Ballard</author>
</authors>
<booktitle>Translating Spanish into Logic through Logic</booktitle>
<volume>6</volume>
<issue>2</issue>
<pages>71--86</pages>
<marker>Biermann, Ballard, </marker>
<rawString>Biermann, Alan W. and Ballard, Bruce W. 6(2): 71-86 Translating Spanish into Logic through Logic</rawString>
</citation>
<citation valid="false">
<authors>
<author>Dahl</author>
</authors>
<title>Veronica 7(3): 149-164 Treating Coordination in Logic Grammars</title>
<marker>Dahl, </marker>
<rawString>Dahl, Veronica 7(3): 149-164 Treating Coordination in Logic Grammars</rawString>
</citation>
<citation valid="false">
<authors>
<author>Veronica Dahl</author>
<author>Michael C McCord</author>
</authors>
<title>Using Semantics in Non-Context-Free Parsing of Montague Grammar</title>
<volume>9</volume>
<issue>2</issue>
<pages>69--91</pages>
<marker>Dahl, McCord, </marker>
<rawString>Dahl, Veronica and McCord, Michael C. 9(2): 69-91 Using Semantics in Non-Context-Free Parsing of Montague Grammar</rawString>
</citation>
<citation valid="false">
<authors>
<author>David Scott Warren</author>
<author>Friedman</author>
</authors>
<pages>8--3</pages>
<marker>Warren, Friedman, </marker>
<rawString>Warren, David Scott and Friedman, Joyce 8(3-4): 123-138</rawString>
</citation>
</citationList>
</algorithm>
</algorithms>