[{"frames":[{"target":{"name":"Intentionally_act","spans":[{"start":12,"end":14,"text":"carried out"}]},"annotationSets":[{"rank":0,"score":69.45386643118636,"frameElements":[{"name":"Agent","spans":[{"start":14,"end":17,"text":"by SINAI group"}]}]}]},{"target":{"name":"Becoming_aware","spans":[{"start":3,"end":4,"text":"Abstract"}]},"annotationSets":[{"rank":0,"score":75.9221811441472,"frameElements":[{"name":"Cognizer","spans":[{"start":0,"end":2,"text":"< newSection"}]},{"name":"Phenomenon","spans":[{"start":4,"end":6,"text":"This document"}]}]}]},{"target":{"name":"Documents","spans":[{"start":5,"end":6,"text":"document"}]},"annotationSets":[{"rank":0,"score":34.227458690979944,"frameElements":[{"name":"Document","spans":[{"start":5,"end":6,"text":"document"}]}]}]},{"target":{"name":"Inclusion","spans":[{"start":6,"end":7,"text":"contains"}]},"annotationSets":[{"rank":0,"score":34.7610957604741,"frameElements":[{"name":"Part","spans":[{"start":7,"end":17,"text":"the description of the experiments carried out by SINAI group"}]},{"name":"Total","spans":[{"start":3,"end":6,"text":"Abstract This document"}]}]}]},{"target":{"name":"Communicate_categorization","spans":[{"start":8,"end":9,"text":"description"}]},"annotationSets":[{"rank":0,"score":39.0796757223457,"frameElements":[{"name":"Item","spans":[{"start":9,"end":17,"text":"of the experiments carried out by SINAI group"}]}]}]},{"target":{"name":"Organization","spans":[{"start":16,"end":17,"text":"group"}]},"annotationSets":[{"rank":0,"score":39.69199236202233,"frameElements":[{"name":"Organization","spans":[{"start":16,"end":17,"text":"group"}]}]}]}],"tokens":["<","newSection",">","Abstract","This","document","contains","the","description","of","the","experiments","carried","out","by","SINAI","group","."]},{"frames":[{"target":{"name":"Cause_to_make_progress","spans":[{"start":2,"end":3,"text":"developed"}]},"annotationSets":[{"rank":0,"score":88.2914497155729,"frameElements":[{"name":"Agent","spans":[{"start":0,"end":1,"text":"We"}]},{"name":"Project","spans":[{"start":3,"end":20,"text":"an approach based on several lexical and syntactic measures integrated by means of different machine learning models"}]}]}]},{"target":{"name":"Means","spans":[{"start":4,"end":5,"text":"approach"}]},"annotationSets":[{"rank":0,"score":21.645494742599034,"frameElements":[]}]},{"target":{"name":"Quantity","spans":[{"start":7,"end":8,"text":"several"}]},"annotationSets":[{"rank":0,"score":25.950477019593677,"frameElements":[{"name":"Quantity","spans":[{"start":7,"end":8,"text":"several"}]},{"name":"Individuals","spans":[{"start":11,"end":12,"text":"measures"}]}]}]},{"target":{"name":"Intentionally_act","spans":[{"start":11,"end":12,"text":"measures"}]},"annotationSets":[{"rank":0,"score":68.2946799689185,"frameElements":[{"name":"Act","spans":[{"start":12,"end":20,"text":"integrated by means of different machine learning models"}]}]}]},{"target":{"name":"Means","spans":[{"start":14,"end":15,"text":"means"}]},"annotationSets":[{"rank":0,"score":16.98014617839416,"frameElements":[{"name":"Means","spans":[{"start":14,"end":20,"text":"means of different machine learning models"}]}]}]},{"target":{"name":"Similarity","spans":[{"start":16,"end":17,"text":"different"}]},"annotationSets":[{"rank":0,"score":45.52921622035586,"frameElements":[]}]},{"target":{"name":"Gizmo","spans":[{"start":17,"end":18,"text":"machine"}]},"annotationSets":[{"rank":0,"score":16.961536653548826,"frameElements":[]}]},{"target":{"name":"Coming_to_believe","spans":[{"start":18,"end":19,"text":"learning"}]},"annotationSets":[{"rank":0,"score":34.05418268124297,"frameElements":[]}]},{"target":{"name":"Vehicle","spans":[{"start":19,"end":20,"text":"models"}]},"annotationSets":[{"rank":0,"score":27.75272626863847,"frameElements":[{"name":"Vehicle","spans":[{"start":19,"end":20,"text":"models"}]}]}]}],"tokens":["We","have","developed","an","approach","based","on","several","lexical","and","syntactic","measures","integrated","by","means","of","different","machine","learning","models","."]},{"frames":[{"target":{"name":"Increment","spans":[{"start":0,"end":1,"text":"More"}]},"annotationSets":[{"rank":0,"score":16.130591321588724,"frameElements":[{"name":"Class","spans":[{"start":1,"end":2,"text":"precisely"}]}]}]},{"target":{"name":"Obviousness","spans":[{"start":1,"end":2,"text":"precisely"}]},"annotationSets":[{"rank":0,"score":32.54015490839213,"frameElements":[{"name":"Degree","spans":[{"start":0,"end":1,"text":"More"}]}]}]},{"target":{"name":"Assessing","spans":[{"start":5,"end":6,"text":"evaluated"}]},"annotationSets":[{"rank":0,"score":87.24476012632057,"frameElements":[{"name":"Assessor","spans":[{"start":3,"end":4,"text":"we"}]},{"name":"Phenomenon","spans":[{"start":6,"end":20,"text":"three features based on lexical similarity and 11 features based on syntactic tree comparison"}]}]}]},{"target":{"name":"Cardinal_numbers","spans":[{"start":6,"end":7,"text":"three"}]},"annotationSets":[{"rank":0,"score":28.71493287498876,"frameElements":[{"name":"Number","spans":[{"start":6,"end":7,"text":"three"}]},{"name":"Entity","spans":[{"start":7,"end":8,"text":"features"}]}]}]},{"target":{"name":"Similarity","spans":[{"start":11,"end":12,"text":"similarity"}]},"annotationSets":[{"rank":0,"score":51.71585217500736,"frameElements":[]}]}],"tokens":["More","precisely",",","we","have","evaluated","three","features","based","on","lexical","similarity","and","11","features","based","on","syntactic","tree","comparison","."]},{"frames":[{"target":{"name":"Candidness","spans":[{"start":5,"end":6,"text":"straightforward"}]},"annotationSets":[{"rank":0,"score":25.592636570022087,"frameElements":[{"name":"Speaker","spans":[{"start":6,"end":7,"text":"approach"}]}]}]},{"target":{"name":"Means","spans":[{"start":6,"end":7,"text":"approach"}]},"annotationSets":[{"rank":0,"score":21.533844749885354,"frameElements":[{"name":"Means","spans":[{"start":6,"end":7,"text":"approach"}]}]}]},{"target":{"name":"Getting","spans":[{"start":9,"end":10,"text":"obtained"}]},"annotationSets":[{"rank":0,"score":62.20173986595283,"frameElements":[{"name":"Recipient","spans":[{"start":7,"end":8,"text":"we"}]},{"name":"Time","spans":[{"start":10,"end":13,"text":"more than 60"}]},{"name":"Theme","spans":[{"start":2,"end":7,"text":"of the relatively straightforward approach"}]}]}]},{"target":{"name":"Increment","spans":[{"start":10,"end":11,"text":"more"}]},"annotationSets":[{"rank":0,"score":18.227081666930914,"frameElements":[{"name":"Class","spans":[{"start":11,"end":12,"text":"than"}]}]}]},{"target":{"name":"Cardinal_numbers","spans":[{"start":12,"end":13,"text":"60"}]},"annotationSets":[{"rank":0,"score":24.097779930377698,"frameElements":[{"name":"Number","spans":[{"start":12,"end":13,"text":"60"}]},{"name":"Entity","spans":[{"start":13,"end":14,"text":"%"}]}]}]},{"target":{"name":"Trust","spans":[{"start":15,"end":16,"text":"accuracy"}]},"annotationSets":[{"rank":0,"score":19.17401600916729,"frameElements":[{"name":"Information","spans":[{"start":15,"end":16,"text":"accuracy"}]}]}]}],"tokens":["In","spite","of","the","relatively","straightforward","approach","we","have","obtained","more","than","60","%","for","accuracy","."]},{"frames":[{"target":{"name":"Relational_quantity","spans":[{"start":11,"end":13,"text":"a good"}]},"annotationSets":[{"rank":0,"score":17.09080274499035,"frameElements":[{"name":"Mass","spans":[{"start":13,"end":14,"text":"result"}]},{"name":"Denoted_quantity","spans":[{"start":12,"end":13,"text":"good"}]}]}]},{"target":{"name":"Ordinal_numbers","spans":[{"start":4,"end":5,"text":"first"}]},"annotationSets":[{"rank":0,"score":17.91579057120894,"frameElements":[{"name":"Type","spans":[{"start":5,"end":6,"text":"participation"}]}]}]},{"target":{"name":"Participation","spans":[{"start":5,"end":6,"text":"participation"}]},"annotationSets":[{"rank":0,"score":49.31908751088062,"frameElements":[]}]},{"target":{"name":"Opinion","spans":[{"start":7,"end":8,"text":"think"}]},"annotationSets":[{"rank":0,"score":48.543485905378674,"frameElements":[{"name":"Cognizer","spans":[{"start":6,"end":7,"text":"we"}]},{"name":"Opinion","spans":[{"start":8,"end":14,"text":"we have reached a good result"}]}]}]},{"target":{"name":"Arriving","spans":[{"start":10,"end":11,"text":"reached"}]},"annotationSets":[{"rank":0,"score":89.95012489990833,"frameElements":[{"name":"Goal","spans":[{"start":11,"end":14,"text":"a good result"}]},{"name":"Theme","spans":[{"start":8,"end":9,"text":"we"}]}]}]},{"target":{"name":"Causation","spans":[{"start":13,"end":14,"text":"result"}]},"annotationSets":[{"rank":0,"score":66.19524843849456,"frameElements":[{"name":"Cause","spans":[{"start":12,"end":13,"text":"good"}]}]}]}],"tokens":["Since","this","is","our","first","participation","we","think","we","have","reached","a","good","result","."]}]